{
	"items": [{
		"title": "Old skkoodsaf.",
		"price": 330,
		"stock": 10,
		"img": "http://lorempixel.com/500/500",
		"id": "58e1302120c73e61b34932b2"
	}, {
		"title": "Old skkoodsaf.",
		"price": 330,
		"stock": 10,
		"img": "http://lorempixel.com/500/500",
		"id": "58e1302120c73e61b34932b3"
	}, {
		"title": "Old skkoodsaf.",
		"price": 330,
		"stock": 10,
		"img": "http://lorempixel.com/500/500",
		"id": "58e1302120c73e61b34932b4"
	}, {
		"title": "Old skkoodsaf.",
		"price": 330,
		"stock": 10,
		"img": "http://lorempixel.com/500/500",
		"id": "58e1302120c73e61b34932b5"
	}],
	"cart": []
}